CHANGES.rst
LICENSE.txt
MANIFEST.in
README.rst
TODO.txt
setup.py
bin/rfw
config/rfw.conf
config/temp.conf
config/white.list
config/deploy/README.rst
config/deploy/rfwgen
config/ssl/PUT_SERVER_KEYS_HERE
rfw/__init__.py
rfw/__init__.pyc
rfw/_version.py
rfw/cmdexe.py
rfw/cmdparse.py
rfw/cmdparse.pyc
rfw/config.py
rfw/config.pyc
rfw/iptables.py
rfw/iptables.pyc
rfw/iputil.py
rfw/iputil.pyc
rfw/rfw.py
rfw/rfw.pyc
rfw/rfwc.py
rfw/rfwconfig.py
rfw/rfwconfig.pyc
rfw/rfwthreads.py
rfw/rfwthreads.pyc
rfw/run_test.py
rfw/sslserver.py
rfw/sslserver.pyc
rfw/timeutil.py
rfw/timeutil.pyc
rfw.egg-info/PKG-INFO
rfw.egg-info/SOURCES.txt
rfw.egg-info/dependency_links.txt
rfw.egg-info/top_level.txt