Metadata-Version: 1.1
Name: rfw
Version: 0.2.2
Summary: Remote firewall as a web service. REST API for iptables.
Home-page: https://github.com/securitykiss-com/rfw
Author: SecurityKISS Ltd
Author-email: open.source@securitykiss.com
License: MIT
Keywords: rfw remote firewall iptables REST web service drop accept ban allow whitelist fail2ban
Platform: UNKNOWN
Classifier: Development Status :: 4 - Beta
Classifier: Environment :: Console
Classifier: Operating System :: POSIX
Classifier: Programming Language :: Python
Classifier: Intended Audience :: System Administrators
Classifier: Topic :: System :: Networking :: Firewalls
Classifier: Topic :: System :: Systems Administration
Classifier: License :: OSI Approved :: MIT License
